chirpstack_api/__init__.py
chirpstack_api/api/__init__.py
chirpstack_api/api/application_pb2.py
chirpstack_api/api/application_pb2_grpc.py
chirpstack_api/api/device_pb2.py
chirpstack_api/api/device_pb2_grpc.py
chirpstack_api/api/device_profile_pb2.py
chirpstack_api/api/device_profile_pb2_grpc.py
chirpstack_api/api/device_profile_template_pb2.py
chirpstack_api/api/device_profile_template_pb2_grpc.py
chirpstack_api/api/frame_log_pb2.py
chirpstack_api/api/frame_log_pb2_grpc.py
chirpstack_api/api/gateway_pb2.py
chirpstack_api/api/gateway_pb2_grpc.py
chirpstack_api/api/internal_pb2.py
chirpstack_api/api/internal_pb2_grpc.py
chirpstack_api/api/multicast_group_pb2.py
chirpstack_api/api/multicast_group_pb2_grpc.py
chirpstack_api/api/relay_pb2.py
chirpstack_api/api/relay_pb2_grpc.py
chirpstack_api/api/request_log_pb2.py
chirpstack_api/api/request_log_pb2_grpc.py
chirpstack_api/api/tenant_pb2.py
chirpstack_api/api/tenant_pb2_grpc.py
chirpstack_api/api/user_pb2.py
chirpstack_api/api/user_pb2_grpc.py
chirpstack_api/common/__init__.py
chirpstack_api/common/common_pb2.py
chirpstack_api/common/common_pb2_grpc.py
chirpstack_api/gw/__init__.py
chirpstack_api/gw/gw_pb2.py
chirpstack_api/gw/gw_pb2_grpc.py
chirpstack_api/integration/__init__.py
chirpstack_api/integration/integration_pb2.py
chirpstack_api/integration/integration_pb2_grpc.py
chirpstack_api/meta/__init__.py
chirpstack_api/meta/meta_pb2.py
chirpstack_api/meta/meta_pb2_grpc.py
chirpstack_api/stream/__init__.py
chirpstack_api/stream/api_request_pb2.py
chirpstack_api/stream/api_request_pb2_grpc.py
chirpstack_api/stream/backend_interfaces_pb2.py
chirpstack_api/stream/backend_interfaces_pb2_grpc.py
chirpstack_api/stream/frame_pb2.py
chirpstack_api/stream/frame_pb2_grpc.py
chirpstack_api/stream/meta_pb2.py
chirpstack_api/stream/meta_pb2_grpc.py
chirpstack_api-4.8.0.dist-info/METADATA
chirpstack_api-4.8.0.dist-info/WHEEL
chirpstack_api-4.8.0.dist-info/top_level.txt
chirpstack_api-4.8.0.dist-info/RECORD
