Metadata-Version: 2.1
Name: chirpstack-api
Version: 4.8.0
Summary: Chirpstack Python API
Home-page: https://github.com/brocaar/chirpstack-api
Author: Orne Brocaar
Author-email: info@brocaar.com
License: MIT
Classifier: Intended Audience :: Developers
Classifier: Operating System :: OS Independent
Classifier: Programming Language :: Python :: 3.7
Classifier: Topic :: Communications
Classifier: Topic :: Software Development
Classifier: Topic :: Software Development :: Libraries
Requires-Dist: grpcio
Requires-Dist: google-api-core
